codelab_adapter_client/.gitignore
codelab_adapter_client/__init__.py
codelab_adapter_client/_version.py
codelab_adapter_client/base.py
codelab_adapter_client/base_aio.py
codelab_adapter_client/cloud_message.py
codelab_adapter_client/config.py
codelab_adapter_client/hass.py
codelab_adapter_client/message.py
codelab_adapter_client/microbit.py
codelab_adapter_client/mqtt_node.py
codelab_adapter_client/session.py
codelab_adapter_client/settings.toml
codelab_adapter_client/simple_node.py
codelab_adapter_client/thing.py
codelab_adapter_client/topic.py
codelab_adapter_client/utils.py
codelab_adapter_client/data/user_settings.toml
codelab_adapter_client/tools/adapter_helper.py
codelab_adapter_client/tools/linda.py
codelab_adapter_client/tools/mdns_browser.py
codelab_adapter_client/tools/mdns_registration.py
codelab_adapter_client/tools/message.json
codelab_adapter_client/tools/monitor.py
codelab_adapter_client/tools/pub.py
codelab_adapter_client/tools/trigger.py
codelab_adapter_client-4.4.2.dist-info/AUTHORS.rst
codelab_adapter_client-4.4.2.dist-info/LICENSE
codelab_adapter_client-4.4.2.dist-info/METADATA
codelab_adapter_client-4.4.2.dist-info/WHEEL
codelab_adapter_client-4.4.2.dist-info/entry_points.txt
codelab_adapter_client-4.4.2.dist-info/top_level.txt
codelab_adapter_client-4.4.2.dist-info/RECORD
