Metadata-Version: 2.1
Name: codelab-adapter-client
Version: 4.4.2
Summary: Python Boilerplate contains all the boilerplate you need to create a Python package.
Home-page: https://github.com/wwj718/codelab_adapter_client
Author: Wenjie Wu
Author-email: wuwenjie718@gmail.com
License: GNU General Public License v3
Keywords: codelab_adapter_client
Platform: UNKNOWN
Classifier: Development Status :: 2 - Pre-Alpha
Classifier: Intended Audience :: Developers
Classifier: License :: OSI Approved :: GNU General Public License v3 (GPLv3)
Classifier: Natural Language :: English
Classifier: Programming Language :: Python :: 2
Classifier: Programming Language :: Python :: 2.7
Classifier: Programming Language :: Python :: 3
Classifier: Programming Language :: Python :: 3.4
Classifier: Programming Language :: Python :: 3.5
Classifier: Programming Language :: Python :: 3.6
Classifier: Programming Language :: Python :: 3.7
Requires-Python: >=3.6.0
Requires-Dist: pyzmq (==20.0.0)
Requires-Dist: msgpack-python (==0.5.6)
Requires-Dist: loguru (==0.5.3)
Requires-Dist: uflash (==1.3.0)
Requires-Dist: zeroconf (==0.28.8)
Requires-Dist: click (==7.1.2)
Requires-Dist: dynaconf (==3.1.2)
Requires-Dist: paho-mqtt (==1.5.1)
